simplekml/__init__.py
simplekml/abstractview.py
simplekml/base.py
simplekml/constants.py
simplekml/coordinates.py
simplekml/featgeom.py
simplekml/icon.py
simplekml/kml.py
simplekml/makeunicode.py
simplekml/model.py
simplekml/networklinkcontrol.py
simplekml/overlay.py
simplekml/region.py
simplekml/schema.py
simplekml/styleselector.py
simplekml/substyle.py
simplekml/timeprimitive.py
simplekml/tour.py
simplekml-1.3.3.dist-info/LICENSE.txt
simplekml-1.3.3.dist-info/METADATA
simplekml-1.3.3.dist-info/WHEEL
simplekml-1.3.3.dist-info/top_level.txt
simplekml-1.3.3.dist-info/RECORD
