Metadata-Version: 2.1
Name: simplekml
Version: 1.3.3
Summary: A Simple KML creator
Home-page: http://readthedocs.org/projects/simplekml/
Author: 2011-2016 Kyle Lancaster | 2019 Patrick Eisoldt
Author-email: patrick@eisoldt.com
License: GNU Lesser General Public License v3+
Platform: UNKNOWN
Classifier: Development Status :: 5 - Production/Stable
Classifier: Programming Language :: Python
Classifier: Programming Language :: Python :: 2.7
Classifier: Programming Language :: Python :: 3
Classifier: Programming Language :: Python :: 3.8
Classifier: License :: OSI Approved :: GNU Lesser General Public License v3 or later (LGPLv3+)
Classifier: Operating System :: OS Independent
Classifier: Topic :: Scientific/Engineering :: GIS
Classifier: Topic :: Software Development :: Libraries :: Python Modules
